wetest/uiautomator2/__init__.py
wetest/uiautomator2/android_driver.py
wetest/uiautomator2/android_element.py
wetest/uiautomator2/installer.py
wetest/uiautomator2/server_runner.py
wetest/uiautomator2/utils.py
wetest/uiautomator2/core/__init__.py
wetest/uiautomator2/core/_adapter.py
wetest/uiautomator2/core/_const.py
wetest/uiautomator2/core/_exceptions.py
wetest/uiautomator2/core/_logger.py
wetest/uiautomator2/core/_request.py
wetest/uiautomator2/core/_selector.py
wetest/uiautomator2/core/_types.py
wetest/uiautomator2/core/_utils.py
wetest/uiautomator2/core/_xpath.py
wetest/uiautomator2/resource/busybox
wetest/uiautomator2/resource/vivo-linux-x86
wetest/uiautomator2/resource/vivo-mac
wetest/uiautomator2/resource/vivo-win.exe
wetest_uiautomator2-1.7.10.dist-info/METADATA
wetest_uiautomator2-1.7.10.dist-info/WHEEL
wetest_uiautomator2-1.7.10.dist-info/top_level.txt
wetest_uiautomator2-1.7.10.dist-info/RECORD
