Metadata-Version: 2.4
Name: wetest-uiautomator2
Version: 1.7.10
Author: Tencent WeTest
Author-email: WeTest@wetest.net
Requires-Python: >=3.7
Requires-Dist: adbutils
Dynamic: author
Dynamic: author-email
Dynamic: description
Dynamic: description-content-type
Dynamic: requires-dist
Dynamic: requires-python
